nrlmsise00/__init__.py
nrlmsise00/_nrlmsise00.cp39-win_amd64.pyd
nrlmsise00/core.py
nrlmsise00/dataset/__init__.py
nrlmsise00/dataset/core.py
nrlmsise00-0.1.2.dist-info/COPYING.GPLv2
nrlmsise00-0.1.2.dist-info/COPYING.NRLMSISE-00
nrlmsise00-0.1.2.dist-info/METADATA
nrlmsise00-0.1.2.dist-info/WHEEL
nrlmsise00-0.1.2.dist-info/top_level.txt
nrlmsise00-0.1.2.dist-info/RECORD
