Metadata-Version: 2.1
Name: nrlmsise00
Version: 0.1.2
Summary: Python interface for the NRLMSISE-00 neutral atmosphere model
Home-page: https://github.com/st-bender/pynrlmsise00
Author: Stefan Bender
Author-email: stefan.bender@ntnu.no
License: GPLv2
Project-URL: Documentation, https://pynrlmsise00.readthedocs.io
Keywords: atmosphere earth model python-interface
Platform: UNKNOWN
Classifier: Development Status :: 4 - Beta
Classifier: Intended Audience :: Science/Research
Classifier: License :: OSI Approved :: GNU General Public License v2 (GPLv2)
Classifier: Operating System :: MacOS :: MacOS X
Classifier: Operating System :: Microsoft :: Windows
Classifier: Operating System :: POSIX :: Linux
Classifier: Programming Language :: Python
Classifier: Programming Language :: Python :: 2
Classifier: Programming Language :: Python :: 3
Classifier: Programming Language :: Python :: Implementation :: CPython
Classifier: Topic :: Scientific/Engineering :: Physics
Classifier: Topic :: Utilities
License-File: COPYING.GPLv2
License-File: COPYING.NRLMSISE-00
Requires-Dist: numpy (>=1.13.0)
Provides-Extra: all
Requires-Dist: pytest ; extra == 'all'
Requires-Dist: spaceweather ; extra == 'all'
Requires-Dist: sphinx (!=3.2.0) ; extra == 'all'
Requires-Dist: xarray ; extra == 'all'
Provides-Extra: dataset
Requires-Dist: spaceweather ; extra == 'dataset'
Requires-Dist: xarray ; extra == 'dataset'
Provides-Extra: docs
Requires-Dist: sphinx (!=3.2.0) ; extra == 'docs'
Provides-Extra: tests
Requires-Dist: pytest ; extra == 'tests'
